.gitignore
CHANGES.txt
README.rst
setup.py
docs/INSTALL.txt
docs/LICENSE.GPL
docs/LICENSE.txt
toutpt/__init__.py
toutpt.zopeskel.egg-info/PKG-INFO
toutpt.zopeskel.egg-info/SOURCES.txt
toutpt.zopeskel.egg-info/dependency_links.txt
toutpt.zopeskel.egg-info/entry_points.txt
toutpt.zopeskel.egg-info/namespace_packages.txt
toutpt.zopeskel.egg-info/not-zip-safe
toutpt.zopeskel.egg-info/requires.txt
toutpt.zopeskel.egg-info/top_level.txt
toutpt/zopeskel/__init__.py
toutpt/zopeskel/collective.py
toutpt/zopeskel/collectivejs.py
toutpt/zopeskel/configure.zcml
toutpt/zopeskel/tests.py
toutpt/zopeskel/theme.py
toutpt/zopeskel/templates/toutpt_collective/+project+-configure.zcml_tmpl
toutpt/zopeskel/templates/toutpt_collective/MANIFEST.in_tmpl
toutpt/zopeskel/templates/toutpt_collective/README.rst_tmpl
toutpt/zopeskel/templates/toutpt_collective/bootstrap.py
toutpt/zopeskel/templates/toutpt_collective/buildout.cfg_tmpl
toutpt/zopeskel/templates/toutpt_collective/gitignore
toutpt/zopeskel/templates/toutpt_collective/setup.py_tmpl
toutpt/zopeskel/templates/toutpt_collective/+namespace_package+/.gitignore
toutpt/zopeskel/templates/toutpt_collective/+namespace_package+/+package+/configure.zcml_tmpl
toutpt/zopeskel/templates/toutpt_collective/+namespace_package+/+package+/rebuild_i18n.sh_tmpl
toutpt/zopeskel/templates/toutpt_collective/+namespace_package+/+package+/testing.py_tmpl
toutpt/zopeskel/templates/toutpt_collective/+namespace_package+/+package+/browser/__init__.py
toutpt/zopeskel/templates/toutpt_collective/+namespace_package+/+package+/browser/configure.zcml_tmpl
toutpt/zopeskel/templates/toutpt_collective/+namespace_package+/+package+/browser/interfaces.py_tmpl
toutpt/zopeskel/templates/toutpt_collective/+namespace_package+/+package+/locales/+namespace_package+.+package+.pot_tmpl
toutpt/zopeskel/templates/toutpt_collective/+namespace_package+/+package+/locales/en/LC_MESSAGES/+namespace_package+.+package+.po_tmpl
toutpt/zopeskel/templates/toutpt_collective/+namespace_package+/+package+/locales/fr/LC_MESSAGES/+namespace_package+.+package+.po_tmpl
toutpt/zopeskel/templates/toutpt_collective/+namespace_package+/+package+/profiles/default/browserlayer.xml_tmpl
toutpt/zopeskel/templates/toutpt_collective/+namespace_package+/+package+/profiles/default/metadata.xml_tmpl
