Metadata-Version: 1.0
Name: toutpt.zopeskel
Version: 1.3.3
Summary: A set of skels for Plone dev
Home-page: https://github.com/toutpt/toutpt.zopeskel
Author: JeanMichel FRANCOIS aka toutpt
Author-email: toutpt@gmail.com
License: GPL
Keywords: paster Plone zopeskel diazo
Platform: UNKNOWN
Classifier: Framework :: Plone
Classifier: Programming Language :: Python
Classifier: Intended Audience :: Developers
